[
    {
        "id": 173161,
        "full_name": "هبه خضر محمود محمد الجحيشي",
        "total_points": 31,
        "graduation_average": 91.237,
        "status": "مرشح",
        "last_auditor_notes": null
    },
    {
        "id": 1567,
        "full_name": "منصور حسين منصور عبدالله محيمد",
        "total_points": 31,
        "graduation_average": 91.192,
        "status": "مرشح",
        "last_auditor_notes": null
    },
    {
        "id": 3375,
        "full_name": "هبه موفق محمود جاسم العبيدي",
        "total_points": 31,
        "graduation_average": 91.141,
        "status": "مرشح",
        "last_auditor_notes": null
    },
    {
        "id": 120304,
        "full_name": "مظهر خضر محمد علي سليمان ال جاسم",
        "total_points": 31,
        "graduation_average": 91.038,
        "status": "مرشح",
        "last_auditor_notes": null
    },
    {
        "id": 138397,
        "full_name": "حيدر  دريد حميد ابراهيم الجبوري",
        "total_points": 31,
        "graduation_average": 90.753,
        "status": "مرشح",
        "last_auditor_notes": null
    },
    {
        "id": 140814,
        "full_name": "اياد فتحي عبدالله رحيل الراشد",
        "total_points": 31,
        "graduation_average": 90.72,
        "status": "مرشح",
        "last_auditor_notes": null
    },
    {
        "id": 114390,
        "full_name": "شهد محمد مشعل محمد هداوه",
        "total_points": 31,
        "graduation_average": 90.69,
        "status": "مرشح",
        "last_auditor_notes": null
    },
    {
        "id": 128088,
        "full_name": "مرح بشار محمد يونس شنشوله",
        "total_points": 31,
        "graduation_average": 90.518,
        "status": "غير مرشح",
        "last_auditor_notes": null
    },
    {
        "id": 491,
        "full_name": "عبدالله  عقبه محمد نوري اغا",
        "total_points": 31,
        "graduation_average": 90.48,
        "status": "مرشح",
        "last_auditor_notes": null
    },
    {
        "id": 189104,
        "full_name": "ابراهيم  ثامر  فاضل  خلف الباباوات",
        "total_points": 31,
        "graduation_average": 90.428,
        "status": "مرشح",
        "last_auditor_notes": null
    },
    {
        "id": 197830,
        "full_name": "مريم عمار هاشم يحيى النعيمي",
        "total_points": 31,
        "graduation_average": 90.413,
        "status": "مرشح",
        "last_auditor_notes": null
    },
    {
        "id": 6069,
        "full_name": "الوليد خالد موسى عاشور العبدالله",
        "total_points": 31,
        "graduation_average": 90.258,
        "status": "مرشح",
        "last_auditor_notes": "تم تعديل معدل التخرج من (90.258) إلى (90.258)"
    },
    {
        "id": 294166,
        "full_name": "احمد رضوان يحيى عبدالله العبدالله",
        "total_points": 31,
        "graduation_average": 90.2,
        "status": "مرشح",
        "last_auditor_notes": "تم تعديل معدل التخرج من (90.2) إلى (90.2)"
    },
    {
        "id": 238783,
        "full_name": "مصطفى  عادل احمد يونس ملا",
        "total_points": 31,
        "graduation_average": 90.169,
        "status": "مرشح",
        "last_auditor_notes": null
    },
    {
        "id": 55884,
        "full_name": "عمار احمد صالح عبدالله سبعاوي",
        "total_points": 31,
        "graduation_average": 90.125,
        "status": "مرشح",
        "last_auditor_notes": null
    },
    {
        "id": 222823,
        "full_name": "سمر فرحان حامد ابراهيم الجدي",
        "total_points": 31,
        "graduation_average": 90.045,
        "status": "مرشح",
        "last_auditor_notes": null
    },
    {
        "id": 127867,
        "full_name": "ساره عبد العزيز نافع عزيز المشهداني",
        "total_points": 31,
        "graduation_average": 89.91,
        "status": "غير مرشح",
        "last_auditor_notes": null
    },
    {
        "id": 150131,
        "full_name": "عبير عبد محمود عبدالله السلطان ",
        "total_points": 31,
        "graduation_average": 89.82,
        "status": "مرشح",
        "last_auditor_notes": "تم تعديل التخصص من (بكلوريوس\\التربية الاساسية\\الجغرافية) إلى (بكلوريوس\\التربية الاساسية\\الجغرافية) وذلك طبقاً للشهادة المرفقة"
    },
    {
        "id": 230916,
        "full_name": " ختام حسين علي دواس الخلف",
        "total_points": 31,
        "graduation_average": 89.65,
        "status": "مرشح",
        "last_auditor_notes": null
    },
    {
        "id": 130643,
        "full_name": "فراس عبدالغني محمدامين عباس جولاق",
        "total_points": 31,
        "graduation_average": 89.544,
        "status": "مرشح",
        "last_auditor_notes": null
    },
    {
        "id": 63239,
        "full_name": "مروه علي  محمد  حماوي الحماوي",
        "total_points": 31,
        "graduation_average": 89.52,
        "status": "مرشح",
        "last_auditor_notes": null
    },
    {
        "id": 189306,
        "full_name": "اسراء محمد عبدالله مصطفى البراتو",
        "total_points": 31,
        "graduation_average": 89.494,
        "status": "مرشح",
        "last_auditor_notes": null
    },
    {
        "id": 166137,
        "full_name": "محمد رمزي حسين علي كيكاني",
        "total_points": 31,
        "graduation_average": 89.448,
        "status": "مرشح",
        "last_auditor_notes": null
    },
    {
        "id": 266010,
        "full_name": "روجي ابراهيم محمد أمين محمد هركي",
        "total_points": 31,
        "graduation_average": 89.1789,
        "status": "مرشح",
        "last_auditor_notes": null
    },
    {
        "id": 163475,
        "full_name": "حنان فارس محمد طاهر محمد سعيد حمو الكلبو",
        "total_points": 31,
        "graduation_average": 88.962,
        "status": "مرشح",
        "last_auditor_notes": null
    },
    {
        "id": 67433,
        "full_name": "طه عبدالحميد  احمد  صالح  الخضير ",
        "total_points": 31,
        "graduation_average": 88.792,
        "status": "مرشح",
        "last_auditor_notes": null
    },
    {
        "id": 199685,
        "full_name": "اكرام محمود علي محمد النداوي",
        "total_points": 31,
        "graduation_average": 88.699,
        "status": "مرشح",
        "last_auditor_notes": null
    },
    {
        "id": 275216,
        "full_name": "امنه سمي محمد خضر العبيدي",
        "total_points": 31,
        "graduation_average": 88.67,
        "status": "مرشح",
        "last_auditor_notes": null
    },
    {
        "id": 244555,
        "full_name": "اركان احمد جمعه عطيه الطائي",
        "total_points": 31,
        "graduation_average": 88.613,
        "status": "مرشح",
        "last_auditor_notes": null
    },
    {
        "id": 111323,
        "full_name": "مهند احمد محمد علي السلطان",
        "total_points": 31,
        "graduation_average": 88.506,
        "status": "مرشح",
        "last_auditor_notes": null
    },
    {
        "id": 258040,
        "full_name": "هدى عبد احمد محيميد سبعاوي",
        "total_points": 31,
        "graduation_average": 88.35,
        "status": "غير مرشح",
        "last_auditor_notes": null
    },
    {
        "id": 144561,
        "full_name": "احمد فاضل عبدالله فرحان الحديدي",
        "total_points": 31,
        "graduation_average": 88.34,
        "status": "مرشح",
        "last_auditor_notes": null
    },
    {
        "id": 173130,
        "full_name": "رفل ممتاز سالم ياسين لايوجد",
        "total_points": 31,
        "graduation_average": 88.244,
        "status": "مرشح",
        "last_auditor_notes": null
    },
    {
        "id": 127311,
        "full_name": "بنيامين  بشير محمد شريف محمد فارس",
        "total_points": 31,
        "graduation_average": 88.227,
        "status": "مرشح",
        "last_auditor_notes": null
    },
    {
        "id": 279119,
        "full_name": "نسمة ياسين عثمان حسين الاحمد",
        "total_points": 31,
        "graduation_average": 88.203,
        "status": "مرشح",
        "last_auditor_notes": "تم تعديل التخصص من (بكلوريوس\\التربية الاساسية\\الجغرافية) إلى (بكلوريوس\\التربية الاساسية\\الجغرافية) وذلك طبقاً للشهادة المرفقة"
    },
    {
        "id": 208901,
        "full_name": "نجاة سلطان صالح احمد الزبيدي",
        "total_points": 31,
        "graduation_average": 88.002,
        "status": "مرشح",
        "last_auditor_notes": null
    },
    {
        "id": 69795,
        "full_name": "شهد ثامر احمد  خلف  الحديدي ",
        "total_points": 31,
        "graduation_average": 87.935,
        "status": "مرشح",
        "last_auditor_notes": null
    },
    {
        "id": 94220,
        "full_name": "رؤى مقداد بشير  طه رزوقي",
        "total_points": 31,
        "graduation_average": 87.59,
        "status": "غير مرشح",
        "last_auditor_notes": null
    },
    {
        "id": 154059,
        "full_name": "ارام عبدالواحد عواد خلف المحبوب",
        "total_points": 31,
        "graduation_average": 87.508,
        "status": "غير مرشح",
        "last_auditor_notes": null
    },
    {
        "id": 284390,
        "full_name": "براء محمود احمد محمود اليحيى",
        "total_points": 31,
        "graduation_average": 87.463,
        "status": "مرشح",
        "last_auditor_notes": "تم تعديل معدل التخرج من (87.463) إلى (87.463)"
    },
    {
        "id": 195787,
        "full_name": "عمار هلال حازم محمد شهاب",
        "total_points": 31,
        "graduation_average": 87.262,
        "status": "مرشح",
        "last_auditor_notes": null
    },
    {
        "id": 156015,
        "full_name": "نور محمد يسن اسماعيل الخفاف",
        "total_points": 31,
        "graduation_average": 87.224,
        "status": "مرشح",
        "last_auditor_notes": null
    },
    {
        "id": 166003,
        "full_name": "زينه فارس حمادي شهاب النعيمي",
        "total_points": 31,
        "graduation_average": 87.15,
        "status": "مرشح",
        "last_auditor_notes": null
    },
    {
        "id": 168291,
        "full_name": "نور  يحيى  حسين  حسن  الزهيري ",
        "total_points": 31,
        "graduation_average": 86.966,
        "status": "غير مرشح",
        "last_auditor_notes": null
    },
    {
        "id": 205999,
        "full_name": "غفران جمال عبدالرزاق محمد البرزنجي",
        "total_points": 31,
        "graduation_average": 86.896,
        "status": "مرشح",
        "last_auditor_notes": null
    },
    {
        "id": 250545,
        "full_name": "ريم حسن محمود حسن عبد الواحد",
        "total_points": 31,
        "graduation_average": 86.829,
        "status": "مرشح",
        "last_auditor_notes": null
    },
    {
        "id": 164431,
        "full_name": "وطبان سلطان احمد خليف النوفل",
        "total_points": 31,
        "graduation_average": 86.815,
        "status": "مرشح",
        "last_auditor_notes": null
    },
    {
        "id": 184693,
        "full_name": "رنا فواز عادل يعقوب يونس اغا",
        "total_points": 31,
        "graduation_average": 86.807,
        "status": "مرشح",
        "last_auditor_notes": null
    },
    {
        "id": 67310,
        "full_name": "الاء عبداللطيف عبدالحميد محمد الحاجم",
        "total_points": 31,
        "graduation_average": 86.806,
        "status": "مرشح",
        "last_auditor_notes": null
    },
    {
        "id": 141367,
        "full_name": "محمد  عارف حسين محمد  الطائي",
        "total_points": 31,
        "graduation_average": 86.79,
        "status": "مرشح",
        "last_auditor_notes": "تم تعديل معدل التخرج من (86.79) إلى (86.79)"
    },
    {
        "id": 177005,
        "full_name": "آية خالد خلف خضر ال ناسو",
        "total_points": 31,
        "graduation_average": 86.788,
        "status": "غير مرشح",
        "last_auditor_notes": null
    },
    {
        "id": 91494,
        "full_name": "أحمد  سليمان حمود سلطان  بلا",
        "total_points": 31,
        "graduation_average": 86.684,
        "status": "مرشح",
        "last_auditor_notes": null
    },
    {
        "id": 150535,
        "full_name": "اسماء حازم علي محمد الهلالي",
        "total_points": 31,
        "graduation_average": 86.625,
        "status": "مرشح",
        "last_auditor_notes": "تم تعديل معدل التخرج من (86.625) إلى (86.625)"
    },
    {
        "id": 2416,
        "full_name": "زهراء  شامل  احمد  ذنون  شوكه",
        "total_points": 31,
        "graduation_average": 86.555,
        "status": "مرشح",
        "last_auditor_notes": null
    },
    {
        "id": 143736,
        "full_name": "تهاني  طه حمزة عباس الاحمد",
        "total_points": 31,
        "graduation_average": 86.47,
        "status": "مرشح",
        "last_auditor_notes": null
    },
    {
        "id": 69405,
        "full_name": "نجم عبدالله احمد صالح الجبوري",
        "total_points": 31,
        "graduation_average": 86.42,
        "status": "مرشح",
        "last_auditor_notes": "تم تعديل معدل التخرج من (86.42) إلى (86.42)"
    },
    {
        "id": 298572,
        "full_name": "دنيا سالم قاسم احمد الشريفي",
        "total_points": 31,
        "graduation_average": 86.396,
        "status": "مرشح",
        "last_auditor_notes": null
    },
    {
        "id": 39813,
        "full_name": "احمد  محمد ابراهيم  احمد المحمد",
        "total_points": 31,
        "graduation_average": 86.372,
        "status": "مرشح",
        "last_auditor_notes": null
    },
    {
        "id": 279863,
        "full_name": "مراز صلاح شریف عدی کاکی",
        "total_points": 31,
        "graduation_average": 86.359,
        "status": "مرشح",
        "last_auditor_notes": null
    },
    {
        "id": 271756,
        "full_name": "نبأ معن حسين علي اللهيبي",
        "total_points": 31,
        "graduation_average": 86.35,
        "status": "غير مرشح",
        "last_auditor_notes": null
    },
    {
        "id": 145043,
        "full_name": "عبدالرحمن  حامد محجوب هلال الامحمد",
        "total_points": 31,
        "graduation_average": 86.247,
        "status": "مرشح",
        "last_auditor_notes": null
    },
    {
        "id": 107764,
        "full_name": "ايه ليث زياد محمد العجم",
        "total_points": 31,
        "graduation_average": 86.2,
        "status": "غير مرشح",
        "last_auditor_notes": null
    },
    {
        "id": 168762,
        "full_name": "حسبي خلف محمد شبلي السلامي",
        "total_points": 31,
        "graduation_average": 86.165,
        "status": "مرشح",
        "last_auditor_notes": null
    },
    {
        "id": 87091,
        "full_name": "محمد  عبدالخالق  مرعي  صوفي  البدراني ",
        "total_points": 31,
        "graduation_average": 86.09,
        "status": "مرشح",
        "last_auditor_notes": null
    },
    {
        "id": 101538,
        "full_name": "ايلاف نجيب محفوظ  محمد العباسي",
        "total_points": 31,
        "graduation_average": 86.009,
        "status": "مرشح",
        "last_auditor_notes": null
    },
    {
        "id": 204767,
        "full_name": "بنيان  شاكر محمود  محمد الخفاجي ",
        "total_points": 31,
        "graduation_average": 85.964,
        "status": "مرشح",
        "last_auditor_notes": null
    },
    {
        "id": 186034,
        "full_name": "اسماء ذنون يونس محمود النعيمي",
        "total_points": 31,
        "graduation_average": 85.911,
        "status": "مرشح",
        "last_auditor_notes": null
    },
    {
        "id": 69112,
        "full_name": "نبأ صميم امجد محمد الحاج محمد",
        "total_points": 31,
        "graduation_average": 85.891,
        "status": "غير مرشح",
        "last_auditor_notes": null
    },
    {
        "id": 204562,
        "full_name": "عثمان رعد عبدالستار علي صالح",
        "total_points": 31,
        "graduation_average": 85.872,
        "status": "مرشح",
        "last_auditor_notes": null
    },
    {
        "id": 138601,
        "full_name": "زينب عبد الاله صالح عباوي الخالدي",
        "total_points": 31,
        "graduation_average": 85.858,
        "status": "مرشح",
        "last_auditor_notes": null
    },
    {
        "id": 86073,
        "full_name": "سمير عبدالرحمن احمد سلطان ال عكيل",
        "total_points": 31,
        "graduation_average": 85.852,
        "status": "مرشح",
        "last_auditor_notes": null
    },
    {
        "id": 21639,
        "full_name": "مصطفى  عبدالوهاب احمد جاسم الحرباوي ",
        "total_points": 31,
        "graduation_average": 85.839,
        "status": "مرشح",
        "last_auditor_notes": null
    },
    {
        "id": 226393,
        "full_name": "الاء  فاضل محمد ابراهيم  الجرجري",
        "total_points": 31,
        "graduation_average": 85.81,
        "status": "مرشح",
        "last_auditor_notes": null
    },
    {
        "id": 236992,
        "full_name": "هبة هاني سعدالله ذوالفقار  ذي الفقار ",
        "total_points": 31,
        "graduation_average": 85.776,
        "status": "مرشح",
        "last_auditor_notes": null
    },
    {
        "id": 88341,
        "full_name": "سلطان ممدوح محمد بشير احسان العباسي",
        "total_points": 31,
        "graduation_average": 85.76,
        "status": "غير مرشح",
        "last_auditor_notes": null
    },
    {
        "id": 133393,
        "full_name": "زينب بشار جاسم  نبراس دليم",
        "total_points": 31,
        "graduation_average": 85.731,
        "status": "مرشح",
        "last_auditor_notes": null
    },
    {
        "id": 181424,
        "full_name": "امنه  عبد اللطيف  محمود  عبد الله  السلطان ",
        "total_points": 31,
        "graduation_average": 85.655,
        "status": "مرشح",
        "last_auditor_notes": null
    },
    {
        "id": 169493,
        "full_name": "سعد سبهان عبدالله يوسف الحمداني",
        "total_points": 31,
        "graduation_average": 85.653,
        "status": "مرشح",
        "last_auditor_notes": null
    },
    {
        "id": 231020,
        "full_name": "ناجي حسين عسل هويدي المحمد",
        "total_points": 31,
        "graduation_average": 85.61,
        "status": "مرشح",
        "last_auditor_notes": null
    },
    {
        "id": 76670,
        "full_name": "امل حمد محمود عابد الجبوري",
        "total_points": 31,
        "graduation_average": 85.603,
        "status": "مرشح",
        "last_auditor_notes": null
    },
    {
        "id": 153633,
        "full_name": "مريم ياسر علي ابراهيم الحمداني",
        "total_points": 31,
        "graduation_average": 85.594,
        "status": "غير مرشح",
        "last_auditor_notes": null
    },
    {
        "id": 170773,
        "full_name": "عزالدين حمود جندي  مديد البدراني",
        "total_points": 31,
        "graduation_average": 85.506,
        "status": "مرشح",
        "last_auditor_notes": null
    },
    {
        "id": 147121,
        "full_name": "اركان محمد علوان مجيد المنصور",
        "total_points": 31,
        "graduation_average": 85.451,
        "status": "مرشح",
        "last_auditor_notes": null
    },
    {
        "id": 240725,
        "full_name": "حنين سالم احمد خضير آل عبدالله",
        "total_points": 31,
        "graduation_average": 85.34,
        "status": "غير مرشح",
        "last_auditor_notes": null
    },
    {
        "id": 159745,
        "full_name": "امل علي خلف ويس الشرابي",
        "total_points": 31,
        "graduation_average": 85.241,
        "status": "مرشح",
        "last_auditor_notes": null
    },
    {
        "id": 188117,
        "full_name": "ازهار محمد محمود محمد امين",
        "total_points": 31,
        "graduation_average": 85.127,
        "status": "مرشح",
        "last_auditor_notes": null
    },
    {
        "id": 253783,
        "full_name": "نبأ  محمد يحيى شريف الطائي",
        "total_points": 31,
        "graduation_average": 85.102,
        "status": "مرشح",
        "last_auditor_notes": null
    },
    {
        "id": 286174,
        "full_name": "نجلاء  عمر فاضل عبد الله  الحرباوي",
        "total_points": 31,
        "graduation_average": 84.944,
        "status": "مرشح",
        "last_auditor_notes": null
    },
    {
        "id": 219321,
        "full_name": "سكينه مسلم حسين حسن الاعرجي",
        "total_points": 31,
        "graduation_average": 84.916,
        "status": "مرشح",
        "last_auditor_notes": null
    },
    {
        "id": 274649,
        "full_name": "زكريا رافع صلاح اسماعيل ال ياسين",
        "total_points": 31,
        "graduation_average": 84.875,
        "status": "مرشح",
        "last_auditor_notes": null
    },
    {
        "id": 205551,
        "full_name": "ماهر محمود عبدالله ذنون العبيدي",
        "total_points": 31,
        "graduation_average": 84.845,
        "status": "مرشح",
        "last_auditor_notes": null
    },
    {
        "id": 188644,
        "full_name": "محمود عبدالله عبدالجبار ذنون المشهداني",
        "total_points": 31,
        "graduation_average": 84.743,
        "status": "مرشح",
        "last_auditor_notes": null
    },
    {
        "id": 96260,
        "full_name": "اهله معن عزيز علي الهنو",
        "total_points": 31,
        "graduation_average": 84.697,
        "status": "مرشح",
        "last_auditor_notes": null
    },
    {
        "id": 191526,
        "full_name": "زيد  ابراهيم احمد مصطفى مصطفى",
        "total_points": 31,
        "graduation_average": 84.674,
        "status": "مرشح",
        "last_auditor_notes": null
    },
    {
        "id": 221451,
        "full_name": "انس  محمد  ادريس حميد اللهيبي",
        "total_points": 31,
        "graduation_average": 84.42,
        "status": "مرشح",
        "last_auditor_notes": null
    },
    {
        "id": 165091,
        "full_name": "عبد الرحمن  تركي  فهد حسين العبد الله ",
        "total_points": 31,
        "graduation_average": 84.373,
        "status": "مرشح",
        "last_auditor_notes": null
    },
    {
        "id": 176200,
        "full_name": "محمد احمد محمد حسن الحسن",
        "total_points": 31,
        "graduation_average": 84.254,
        "status": "مرشح",
        "last_auditor_notes": "تم تعديل معدل التخرج من (84.254) إلى (84.254)"
    },
    {
        "id": 72527,
        "full_name": "نور محمود جرجيس يحيى الكواز",
        "total_points": 31,
        "graduation_average": 84.179,
        "status": "مرشح",
        "last_auditor_notes": null
    },
    {
        "id": 17414,
        "full_name": "محمد عمار عبدالوهاب احمد لايوجد",
        "total_points": 31,
        "graduation_average": 84.01,
        "status": "مرشح",
        "last_auditor_notes": null
    },
    {
        "id": 69837,
        "full_name": "فنر عبد حمدي صالح الصبيح",
        "total_points": 31,
        "graduation_average": 83.898,
        "status": "مرشح",
        "last_auditor_notes": null
    }
]